[{"id":"SolarResistance000","ability":"Resistance","name":"Durability of Oak Meditation","cost":"3m;","ability_min":2,"essence_min":1,"type":"Reflexive","keywords":"Dual","duration":"One tick","prereqs":[]},{"id":"SolarResistance001","ability":"Resistance","name":"Spirit Strengthens the Skin","cost":"1m per damage die removed;","ability_min":2,"essence_min":1,"type":"Reflexive","keywords":"Withering-only","duration":"Instant","prereqs":["SolarResistance000"]},{"id":"SolarResistance002","ability":"Resistance","name":"Iron Skin Concentration","cost":"2m or 6m;","ability_min":3,"essence_min":1,"type":"Reflexive","keywords":"Dual","duration":"Instant or Indefinite","prereqs":["SolarResistance001"]},{"id":"SolarResistance003","ability":"Resistance","name":"Ox-Body Technique","cost":";","ability_min":1,"essence_min":1,"type":"Permanent","keywords":"Stackable","duration":"Permanent","prereqs":[]},{"id":"SolarResistance004","ability":"Resistance","name":"Body-Mending Meditation","cost":"10m;","ability_min":2,"essence_min":1,"type":"Simple","keywords":"Mute","duration":"Instant","prereqs":["SolarResistance003"]},{"id":"SolarResistance005","ability":"Resistance","name":"Front-Line Warrior’s Stamina","cost":"4m;","ability_min":3,"essence_min":1,"type":"Simple","keywords":"Perilous","duration":"Instant","prereqs":["SolarResistance003"]},{"id":"SolarResistance006","ability":"Resistance","name":"Whirlwind Armor-Donning Prana","cost":"2m;","ability_min":1,"essence_min":1,"type":"Simple","keywords":"None","duration":"Instant","prereqs":[]},{"id":"SolarResistance007","ability":"Resistance","name":"Armored Scout’s Invigoration","cost":"4m or 6m;","ability_min":3,"essence_min":1,"type":"Reflexive","keywords":"None","duration":"Indefinite","prereqs":["SolarResistance006"]},{"id":"SolarResistance008","ability":"Resistance","name":"Poison-Resisting Meditation","cost":"3m;","ability_min":3,"essence_min":1,"type":"Reflexive","keywords":"None","duration":"One scene","prereqs":[]},{"id":"SolarResistance009","ability":"Resistance","name":"Essence-Gathering Temper","cost":"1i;","ability_min":3,"essence_min":1,"type":"Reflexive","keywords":"Perilous, Withering-only","duration":"Instant","prereqs":[]},{"id":"SolarResistance010","ability":"Resistance","name":"Diamond-Body Prana","cost":"5m;","ability_min":4,"essence_min":2,"type":"Simple","keywords":"Dual","duration":"One scene","prereqs":["SolarResistance002"]},{"id":"SolarResistance011","ability":"Resistance","name":"Iron Kettle Body","cost":"6m;","ability_min":4,"essence_min":2,"type":"Reflexive","keywords":"Withering-only","duration":"One turn","prereqs":["SolarResistance002"]},{"id":"SolarResistance012","ability":"Resistance","name":"Adamant Skin Technique","cost":"8m;","ability_min":5,"essence_min":2,"type":"Reflexive","keywords":"Decisive-only","duration":"Instant","prereqs":["SolarResistance010","SolarResistance011"]},{"id":"SolarResistance013","ability":"Resistance","name":"Tiger Warrior’s Endurance","cost":";","ability_min":5,"essence_min":2,"type":"Permanent","keywords":"None","duration":"Permanent","prereqs":["SolarResistance004","SolarResistance005"]},{"id":"SolarResistance014","ability":"Resistance","name":"Hauberk-Summoning Gesture","cost":"3m;","ability_min":3,"essence_min":2,"type":"Reflexive","keywords":"None","duration":"Instant","prereqs":["SolarResistance006"]},{"id":"SolarResistance015","ability":"Resistance","name":"Illness-Resisting Meditation","cost":"4m;","ability_min":4,"essence_min":2,"type":"Reflexive","keywords":"None","duration":"One day","prereqs":["SolarResistance008"]},{"id":"SolarResistance016","ability":"Resistance","name":"Willpower-Enhancing Spirit","cost":"2i;","ability_min":4,"essence_min":2,"type":"","keywords":"Perilous, Decisive-only","duration":"Instant","prereqs":["SolarResistance009"]},{"id":"SolarResistance017","ability":"Resistance","name":"Battle Fury Focus","cost":"5m;","ability_min":5,"essence_min":2,"type":"Simple","keywords":"None","duration":"One scene","prereqs":["SolarResistance016"]},{"id":"SolarResistance018","ability":"Resistance","name":"Wound-Knitting Exercise","cost":"1m per -0 health level;","ability_min":5,"essence_min":3,"type":"Simple","keywords":"None","duration":"Until fully healed","prereqs":["SolarResistance013"]},{"id":"SolarResistance019","ability":"Resistance","name":"Unbreakable Warrior’s Mastery","cost":"3m;","ability_min":5,"essence_min":3,"type":"Reflexive","keywords":"None","duration":"Instant","prereqs":["SolarResistance018"]},{"id":"SolarResistance020","ability":"Resistance","name":"Ruin-Abasing Shrug","cost":"4m;","ability_min":5,"essence_min":3,"type":"Reflexive","keywords":"Decisive-only","duration":"Instant","prereqs":["SolarResistance012"]},{"id":"SolarResistance021","ability":"Resistance","name":"Glorious Solar Plate","cost":"10m, 1wp;","ability_min":4,"essence_min":3,"type":"Simple","keywords":"None","duration":"Indefinite","prereqs":["SolarResistance014"]},{"id":"SolarResistance022","ability":"Resistance","name":"Immunity to Everything Technique","cost":"6m, 1wp;","ability_min":5,"essence_min":3,"type":"Reflexive","keywords":"None","duration":"One day","prereqs":["SolarResistance015"]},{"id":"SolarResistance023","ability":"Resistance","name":"Fury-Fed Ardor","cost":"3m, 1wp;","ability_min":5,"essence_min":3,"type":"","keywords":"Decisive-only","duration":"Instant","prereqs":["SolarResistance016"]},{"id":"SolarResistance024","ability":"Resistance","name":"Bloodthirsty Sword-Dancer Spirit","cost":"10m, 1wp;","ability_min":5,"essence_min":3,"type":"Simple","keywords":"None","duration":"One scene","prereqs":["SolarResistance017"]},{"id":"SolarResistance025","ability":"Resistance","name":"Aegis of Invincible Might","cost":";","ability_min":5,"essence_min":5,"type":"Permanent","keywords":"Dual, Perilous","duration":"Permanent","prereqs":["SolarResistance012"]}]